setup.cfg
setup.py
Tessellation_Station.egg-info/PKG-INFO
Tessellation_Station.egg-info/SOURCES.txt
Tessellation_Station.egg-info/dependency_links.txt
Tessellation_Station.egg-info/entry_points.txt
Tessellation_Station.egg-info/requires.txt
Tessellation_Station.egg-info/top_level.txt
tessellation_station/__init__.py
tessellation_station/command_line.py
tessellation_station/coordinate_grid.py
tessellation_station/main.py
tessellation_station/transformations.py