Metadata-Version: 1.1
Name: Tessellation-Station
Version: 1.0
Summary: Basic polygon tessellation on the command line
Home-page: https://github.com/edison-moreland/Tessellation-Station
Author: Edison Moreland
Author-email: edison@devdude.net
License: MIT
Download-URL: https://github.com/edison-moreland/Tessellation-Station/archive/1.0.0.tar.gz
Platform: UNKNOWN
